pycgettbcli.py
pycgettb/__init__.py
pycgettb-0.1.2.dist-info/DESCRIPTION.rst
pycgettb-0.1.2.dist-info/LICENSE.txt
pycgettb-0.1.2.dist-info/METADATA
pycgettb-0.1.2.dist-info/RECORD
pycgettb-0.1.2.dist-info/WHEEL
pycgettb-0.1.2.dist-info/entry_points.txt
pycgettb-0.1.2.dist-info/metadata.json
pycgettb-0.1.2.dist-info/top_level.txt
