Metadata-Version: 2.0
Name: pycgettb
Version: 0.1.2
Summary: convert guided form excel to text data by template base
Home-page: https://github.com/hrsano645/pycgettb
Author: Hiroshi Sano
Author-email: hrs.sano645@gmail.com
License: MIT
Keywords: excel xlsx convert jinja2 template
Platform: UNKNOWN
Classifier: Development Status :: 3 - Alpha
Classifier: Intended Audience :: Developers
Classifier: Topic :: Software Development :: Libraries :: Python Modules
Classifier: License :: OSI Approved :: MIT License
Classifier: Programming Language :: Python :: 2
Classifier: Programming Language :: Python :: 2.7
Classifier: Programming Language :: Python :: 3
Classifier: Programming Language :: Python :: 3.6
Requires-Dist: jinja2
Requires-Dist: click
Requires-Dist: openpyxl
